__init__.py
core.py
f4compete-0.1.1.dist-info/METADATA
f4compete-0.1.1.dist-info/WHEEL
f4compete-0.1.1.dist-info/top_level.txt
f4compete-0.1.1.dist-info/RECORD
