Metadata-Version: 2.4
Name: f4compete
Version: 0.1.1
Requires-Python: >=3.7
Requires-Dist: g4f
